{"results":[{"desc":"PAINT VERKEHRSGRAU A (TRAFFIC GREY A)","formula":"RAL7042","view":{"en":"HTTPS://IMAGES.HILLYARD.COM/IMAGES/MSDS/MSDSVARIOUS.PDF","es":"HTTPS://IMAGES.HILLYARD.COM/IMAGES/MSDS/ESPVARIOUS.PDF"},"ingredients":{"en":null}},{"desc":"A BEN A QUI 1LB TUB","formula":"GMNCD2416ABQ","view":{"en":"HTTPS://IMAGES.HILLYARD.COM/IMAGES/MSDS/MSDSGMNCD2416ABQ.PDF","es":"HTTPS://IMAGES.HILLYARD.COM/IMAGES/MSDS/ESPSGMNCD2416ABQ.PDF"},"ingredients":{"en":null}},{"desc":"UPHOLD-PT A","formula":"PART28935A","view":{"en":"HTTPS://IMAGES.HILLYARD.COM/IMAGES/MSDS/MSDSPART28900A.PDF","es":"HTTPS://IMAGES.HILLYARD.COM/IMAGES/MSDS/ESPSPART28900A.PDF"},"ingredients":{"en":"HTTPS://APPSWEB.HILLYARD.COM/INGREDIENT?FORMULA=PART28900A"}},{"desc":"BATTERY TYPE A","formula":"EXI526R","view":{"en":"HTTPS://IMAGES.HILLYARD.COM/IMAGES/MSDS/MSDSBATUB123.PDF","es":"HTTPS://IMAGES.HILLYARD.COM/IMAGES/MSDS/ESPSBATUB123.PDF"},"ingredients":{"en":null}},{"desc":"STICK A FLY RIBBON ON A ROLL 12CS","formula":"JTE442","view":{"en":"HTTPS://IMAGES.HILLYARD.COM/IMAGES/MSDS/MSDSJTE122.PDF","es":"HTTPS://IMAGES.HILLYARD.COM/IMAGES/MSDS/ESPSJTE122.PDF"},"ingredients":{"en":null}},{"desc":"PRO SATIN-PT A","formula":"PART75835A","view":{"en":"HTTPS://IMAGES.HILLYARD.COM/IMAGES/MSDS/MSDSPART75800A.PDF","es":"HTTPS://IMAGES.HILLYARD.COM/IMAGES/MSDS/ESPSPART75800A.PDF"},"ingredients":{"en":null}},{"desc":"$REMOVEUPHOLD PART A BULK","formula":"PART28900A","view":{},"ingredients":{}},{"desc":"$REMOVEICON PART A BULK","formula":"PART27400A","view":{},"ingredients":{}},{"desc":"$REMOVE275 CONTENDER PART A","formula":"HIL8820100","view":{},"ingredients":{}},{"desc":"BATTERY 12V195 A/H","formula":"VIPBAT1951","view":{"en":"HTTPS://IMAGES.HILLYARD.COM/IMAGES/MSDS/MSDSBRY4D3.PDF","es":"HTTPS://IMAGES.HILLYARD.COM/IMAGES/MSDS/ESPSBRY4D3.PDF"},"ingredients":{"en":null}},{"desc":"BATTERY 12V105 A/H","formula":"VIPBAT1051","view":{"en":"HTTPS://IMAGES.HILLYARD.COM/IMAGES/MSDS/MSDSBRY4D3.PDF","es":"HTTPS://IMAGES.HILLYARD.COM/IMAGES/MSDS/ESPSBRY4D3.PDF"},"ingredients":{"en":null}},{"desc":"CLEANER FOAMY Q & A","formula":"SPA320004","view":{"en":"HTTPS://IMAGES.HILLYARD.COM/IMAGES/MSDS/MSDSSPA320004.PDF","es":"HTTPS://IMAGES.HILLYARD.COM/IMAGES/MSDS/ESPSSPA320004.PDF"},"ingredients":{"en":null}},{"desc":"A EXCELL ACID CLEANER","formula":"CFR3BM003","view":{"en":"HTTPS://IMAGES.HILLYARD.COM/IMAGES/MSDS/MSDSCFR3BM005.PDF","es":"HTTPS://IMAGES.HILLYARD.COM/IMAGES/MSDS/ESPSCFR3BM005.PDF"},"ingredients":{"en":null}},{"desc":"A EXCELL 5 GL","formula":"CFR3BM005","view":{"en":"HTTPS://IMAGES.HILLYARD.COM/IMAGES/MSDS/MSDSCFR3BM005.PDF","es":"HTTPS://IMAGES.HILLYARD.COM/IMAGES/MSDS/ESPSCFR3BM005.PDF"},"ingredients":{"en":null}},{"desc":"$REMOVEICON PART A BULK","formula":"HIL0020500","view":{},"ingredients":{}},{"desc":"DOUBLE DOWN PART A","formula":"HIL0098068","view":{"en":"HTTPS://IMAGES.HILLYARD.COM/IMAGES/MSDS/MSDSHIL00932.PDF","es":"HTTPS://IMAGES.HILLYARD.COM/IMAGES/MSDS/ESPSHIL00932.PDF"},"ingredients":{"en":null}},{"desc":"LAUNDRY RECLAIM KIT A","formula":"EBP448200306","view":{"en":"HTTPS://IMAGES.HILLYARD.COM/IMAGES/MSDS/MSDSEBP448200306.PDF","es":"HTTPS://IMAGES.HILLYARD.COM/IMAGES/MSDS/ESPSEBP448200306.PDF"},"ingredients":{"en":null}},{"desc":"BATTERY DISCOVERY EVGC6A-A","formula":"HBC4001","view":{"en":"HTTPS://IMAGES.HILLYARD.COM/IMAGES/MSDS/MSDSALT05361A.PDF","es":"HTTPS://IMAGES.HILLYARD.COM/IMAGES/MSDS/ESPSALT05361A.PDF"},"ingredients":{"en":null}},{"desc":"BATTERY DISCOVERY EV185A-A","formula":"HBC4025","view":{"en":"HTTPS://IMAGES.HILLYARD.COM/IMAGES/MSDS/MSDSALT05361A.PDF","es":"HTTPS://IMAGES.HILLYARD.COM/IMAGES/MSDS/ESPSALT05361A.PDF"},"ingredients":{"en":null}},{"desc":"ICON PART A 5 GAL","formula":"PART27407A","view":{"en":"HTTPS://IMAGES.HILLYARD.COM/IMAGES/MSDS/MSDSHIL00274 PART A.PDF","es":"HTTPS://IMAGES.HILLYARD.COM/IMAGES/MSDS/ESPHIL00274 PART A.PDF"},"ingredients":{"en":null}},{"desc":"DEODORANT TAP A DROP ORIGINAL","formula":"NIL400NC","view":{"en":"HTTPS://IMAGES.HILLYARD.COM/IMAGES/MSDS/MSDSNIL400NC.PDF","es":"HTTPS://IMAGES.HILLYARD.COM/IMAGES/MSDS/ESPSNIL400NC.PDF"},"ingredients":{"en":null}},{"desc":"275 CONTENDER FINISH Pt A","formula":"HIL8820175","view":{"en":"HTTPS://IMAGES.HILLYARD.COM/IMAGES/MSDS/MSDSHIL88279 PART A.PDF","es":"HTTPS://IMAGES.HILLYARD.COM/IMAGES/MSDS/ESPSHIL88279 PART A.PDF"},"ingredients":{"en":null}},{"desc":"ICON PART A 5 GAL","formula":"HIL0020574","view":{"en":"HTTPS://IMAGES.HILLYARD.COM/IMAGES/MSDS/MSDSHIL00205.PDF","es":"HTTPS://IMAGES.HILLYARD.COM/IMAGES/MSDS/ESPSHIL00205.PDF"},"ingredients":{"en":null}},{"desc":"$REMOVEDOUBLE DOWN PART A BULK","formula":"HIL0098000","view":{},"ingredients":{}},{"desc":"ICON PART A 5 GALLON","formula":"PART27472A","view":{"en":"HTTPS://IMAGES.HILLYARD.COM/IMAGES/MSDS/MSDSHIL00274 PART A.PDF","es":"HTTPS://IMAGES.HILLYARD.COM/IMAGES/MSDS/ESPHIL00274 PART A.PDF"},"ingredients":{"en":null}},{"desc":"LIQUID TRIPLE A  5 GAL PAIL","formula":"UNX119959","view":{"en":"HTTPS://IMAGES.HILLYARD.COM/IMAGES/MSDS/MSDSUNX119953.PDF","es":"HTTPS://IMAGES.HILLYARD.COM/IMAGES/MSDS/ESPSUNX119953.PDF"},"ingredients":{"en":null}},{"desc":"CLEANER CARPET SPIN A WAY 4X1","formula":"SPE4211206","view":{"en":"HTTPS://IMAGES.HILLYARD.COM/IMAGES/MSDS/MSDSSPE4211206.PDF","es":"HTTPS://IMAGES.HILLYARD.COM/IMAGES/MSDS/ESPSSPE4211206.PDF"},"ingredients":{"en":null}},{"desc":"$REMOVEX-PRODUCT CONTENDER PT A BULK","formula":"HIL1085200","view":{},"ingredients":{}},{"desc":"ALKALI-A PWDRED ORTHOSILICATE BLDER 50LB","formula":"UNX3821","view":{"en":"HTTPS://IMAGES.HILLYARD.COM/IMAGES/MSDS/MSDSUNX3821.PDF","es":"HTTPS://IMAGES.HILLYARD.COM/IMAGES/MSDS/ESPSUNX3821.PDF"},"ingredients":{"en":null}},{"desc":"FOAMY Q & A 12 PER CASE","formula":"SPA3200","view":{"en":"HTTPS://IMAGES.HILLYARD.COM/IMAGES/MSDS/MSDSSPA320004.PDF","es":"HTTPS://IMAGES.HILLYARD.COM/IMAGES/MSDS/ESPSSPA320004.PDF"},"ingredients":{"en":null}},{"desc":"CFR BW STAIN A WAY PINT","formula":"CFR3AI001","view":{"en":"HTTPS://IMAGES.HILLYARD.COM/IMAGES/MSDS/MSDSCFR72266A.PDF","es":"HTTPS://IMAGES.HILLYARD.COM/IMAGES/MSDS/ESPSCFR72266A.PDF"},"ingredients":{"en":null}},{"desc":"HERBICIDE CONCEN WEED A CIDE GAL","formula":"AMRR58301","view":{"en":"HTTPS://IMAGES.HILLYARD.COM/IMAGES/MSDS/MSDSAMRR58307.PDF","es":"HTTPS://IMAGES.HILLYARD.COM/IMAGES/MSDS/ESPSAMRR58307.PDF"},"ingredients":{"en":null}},{"desc":"SCRUBS IN A BUCKET 72 BUCKET","formula":"DYMDC422","view":{"en":"HTTPS://IMAGES.HILLYARD.COM/IMAGES/MSDS/MSDSDYM42272.PDF","es":"HTTPS://IMAGES.HILLYARD.COM/IMAGES/MSDS/ESPSDYM42272.PDF"},"ingredients":{"en":null}},{"desc":"BATTERY LEAD ACID 155 A/H","formula":"HBCT1275","view":{"en":"HTTPS://IMAGES.HILLYARD.COM/IMAGES/MSDS/MSDSTROJ185E.PDF","es":"HTTPS://IMAGES.HILLYARD.COM/IMAGES/MSDS/ESPSTROJ185E.PDF"},"ingredients":{"en":null}},{"desc":"FIRE RETARDANT INSPECT A SHIELD 4GAL CS","formula":"NYFISP06","view":{"en":"HTTPS://IMAGES.HILLYARD.COM/IMAGES/MSDS/MSDSNYFISP06.PDF","es":"HTTPS://IMAGES.HILLYARD.COM/IMAGES/MSDS/ESPSNYFISP06.PDF"},"ingredients":{"en":null}},{"desc":"ICON PT A FOR 1 GAL 274","formula":"PART27406A","view":{"en":"HTTPS://IMAGES.HILLYARD.COM/IMAGES/MSDS/MSDSHIL00274 PART A.PDF","es":"HTTPS://IMAGES.HILLYARD.COM/IMAGES/MSDS/ESPHIL00274 PART A.PDF"},"ingredients":{"en":null}},{"desc":"DEODORANT TAP A DROP RED CLOVER TEA","formula":"NIL404NC","view":{"en":"HTTPS://IMAGES.HILLYARD.COM/IMAGES/MSDS/MSDSNIL400NC.PDF","es":"HTTPS://IMAGES.HILLYARD.COM/IMAGES/MSDS/ESPSNIL400NC.PDF"},"ingredients":{"en":null}},{"desc":"45 LB CONTAINER OF STAIN OUT A","formula":"PSYC36001","view":{"en":"HTTPS://IMAGES.HILLYARD.COM/IMAGES/MSDS/MSDSPSYC36001.PDF","es":"HTTPS://IMAGES.HILLYARD.COM/IMAGES/MSDS/ESPSPSYC36001.PDF"},"ingredients":{"en":null}},{"desc":"EATON STICK A FLY FLY TRAPS 12CS","formula":"JTE444","view":{"en":"HTTPS://IMAGES.HILLYARD.COM/IMAGES/MSDS/MSDSJTE122.PDF","es":"HTTPS://IMAGES.HILLYARD.COM/IMAGES/MSDS/ESPSJTE122.PDF"},"ingredients":{"en":null}},{"desc":"275 CONTENDER FINISH Pt A 5 GAL","formula":"HIL8820176","view":{"en":"HTTPS://IMAGES.HILLYARD.COM/IMAGES/MSDS/MSDSHIL88279 PART A.PDF","es":"HTTPS://IMAGES.HILLYARD.COM/IMAGES/MSDS/ESPSHIL88279 PART A.PDF"},"ingredients":{"en":null}},{"desc":"DETERGENT LIQUID TRIPLE A MACH 4X1/CS","formula":"UNX119953","view":{"en":"HTTPS://IMAGES.HILLYARD.COM/IMAGES/MSDS/MSDSUNX119953.PDF","es":"HTTPS://IMAGES.HILLYARD.COM/IMAGES/MSDS/ESPSUNX119953.PDF"},"ingredients":{"en":null}},{"desc":"AUTOSCRUBBER SABER COMPACT 16 A/H BAT","formula":"WIN98405310","view":{"en":"HTTPS://IMAGES.HILLYARD.COM/IMAGES/MSDS/MSDSTROJ185E.PDF","es":"HTTPS://IMAGES.HILLYARD.COM/IMAGES/MSDS/ESPSTROJ185E.PDF"},"ingredients":{"en":null}},{"desc":"POLISH STONE MEDIC A 500 MULTI SURFACE","formula":"VIC25801","view":{"en":"HTTPS://IMAGES.HILLYARD.COM/IMAGES/MSDS/MSDSVIC25801.PDF","es":"HTTPS://IMAGES.HILLYARD.COM/IMAGES/MSDS/ESPSVIC25801.PDF"},"ingredients":{"en":null}},{"desc":"FOAMY Q & A BOTTLES 12 PER CASE","formula":"SPA006062","view":{"en":"HTTPS://IMAGES.HILLYARD.COM/IMAGES/MSDS/MSDSSPA006062.PDF","es":"HTTPS://IMAGES.HILLYARD.COM/IMAGES/MSDS/ESPSSPA006062.PDF"},"ingredients":{"en":null}},{"desc":"CLEANER DISINFECTANT FOAMY Q & A RTU 12/","formula":"SPN320012","view":{"en":"HTTPS://IMAGES.HILLYARD.COM/IMAGES/MSDS/MSDSSPN320204.PDF","es":"HTTPS://IMAGES.HILLYARD.COM/IMAGES/MSDS/ESPSSPN320204.PDF"},"ingredients":{"en":null}},{"desc":"LIME A WAY FLIP TOP 28OZ 6CS","formula":"REC87000","view":{"en":"HTTPS://IMAGES.HILLYARD.COM/IMAGES/MSDS/MSDSREC87000.PDF","es":"HTTPS://IMAGES.HILLYARD.COM/IMAGES/MSDS/ESPSREC87000.PDF"},"ingredients":{"en":null}},{"desc":"LIME A WAY IMPACT TRIGGER 22OZ 6CS","formula":"REC87103","view":{"en":"HTTPS://IMAGES.HILLYARD.COM/IMAGES/MSDS/MSDSREC87103.PDF","es":"HTTPS://IMAGES.HILLYARD.COM/IMAGES/MSDS/ESPSREC87103.PDF"},"ingredients":{"en":null}},{"desc":"CARPET CLNER PROGRESS A CLEAN 12PK 4CS","formula":"SSY2112PAC","view":{"en":"HTTPS://IMAGES.HILLYARD.COM/IMAGES/MSDS/MSDSSSY2112PAC.PDF","es":"HTTPS://IMAGES.HILLYARD.COM/IMAGES/MSDS/ESPSSSY2112PAC.PDF"},"ingredients":{"en":null}},{"desc":"SPOTTER GENERAL SPTTR A RELEASE RTU 32OZ","formula":"ANDPYL7009","view":{"en":"HTTPS://IMAGES.HILLYARD.COM/IMAGES/MSDS/MSDSANDPYL7009.PDF","es":"HTTPS://IMAGES.HILLYARD.COM/IMAGES/MSDS/ESPSANDPYL7009.PDF"},"ingredients":{"en":null}},{"desc":"HERBICIDE CONC WEED A CIDE 5 GAL","formula":"AMRR58307","view":{"en":"HTTPS://IMAGES.HILLYARD.COM/IMAGES/MSDS/MSDSAMRR58307.PDF","es":"HTTPS://IMAGES.HILLYARD.COM/IMAGES/MSDS/ESPSAMRR58307.PDF"},"ingredients":{"en":null}},{"desc":"ICON PT A FOR 1 GAL 274","formula":"HIL0020573","view":{"en":"HTTPS://IMAGES.HILLYARD.COM/IMAGES/MSDS/MSDSHIL00274 PART A.PDF","es":"HTTPS://IMAGES.HILLYARD.COM/IMAGES/MSDS/ESPSHIL00274 PART A.PDF"},"ingredients":{"en":null}},{"desc":"CONCRETE SEAL HVY TRAFFIC BEIGE PT A QT","formula":"PART50269A","view":{"en":"HTTPS://IMAGES.HILLYARD.COM/IMAGES/MSDS/MSDSHIL00502PARTA.PDF","es":"HTTPS://IMAGES.HILLYARD.COM/IMAGES/MSDS/ESPHIL00502PARTA.PDF"},"ingredients":{"en":null}},{"desc":"CONCRETE SEAL HEAVY TRAF CLR HTC-PT A","formula":"PART49306A","view":{"en":"HTTPS://IMAGES.HILLYARD.COM/IMAGES/MSDS/MSDSHIL00493 PART A.PDF","es":"HTTPS://IMAGES.HILLYARD.COM/IMAGES/MSDS/ESPSHIL00493 PART A.PDF"},"ingredients":{"en":null}},{"desc":"CONCRETE SEAL HEAVY TRAF-CLR HTC-PT A","formula":"PART49307A","view":{"en":"HTTPS://IMAGES.HILLYARD.COM/IMAGES/MSDS/MSDSHIL00493 PART A.PDF","es":"HTTPS://IMAGES.HILLYARD.COM/IMAGES/MSDS/ESPSHIL00493 PART A.PDF"},"ingredients":{"en":null}},{"desc":"$REMOVECONCRETE SEAL HEAVY TRAF-GRAY PT A BULK","formula":"PART50000A","view":{},"ingredients":{}},{"desc":"LIME A WAY GEL FLIP TOP 28OZ 9CS","formula":"REC39605","view":{"en":"HTTPS://IMAGES.HILLYARD.COM/IMAGES/MSDS/MSDSREC39605.PDF","es":"HTTPS://IMAGES.HILLYARD.COM/IMAGES/MSDS/ESPSREC39605.PDF"},"ingredients":{"en":null}},{"desc":"SALT DEICING ICE A WAY 25 LB BAG","formula":"IRM25100","view":{"en":"HTTPS://IMAGES.HILLYARD.COM/IMAGES/MSDS/MSDSIRM25100.PDF","es":"HTTPS://IMAGES.HILLYARD.COM/IMAGES/MSDS/ESPSIRM25100.PDF"},"ingredients":{"en":null}},{"desc":"WAREWASH TRIPLE A  MACH DET 4X7.5 LB CS","formula":"UNX26896","view":{"en":"HTTPS://IMAGES.HILLYARD.COM/IMAGES/MSDS/MSDSUNX26896.PDF","es":"HTTPS://IMAGES.HILLYARD.COM/IMAGES/MSDS/ESPSUNX26896.PDF"},"ingredients":{"en":null}},{"desc":"CLEANER DISINFECTANT FOAMY Q & A RTU 4/C","formula":"SPN320204","view":{"en":"HTTPS://IMAGES.HILLYARD.COM/IMAGES/MSDS/MSDSSPN320204.PDF","es":"HTTPS://IMAGES.HILLYARD.COM/IMAGES/MSDS/ESPSSPN320204.PDF"},"ingredients":{"en":null}},{"desc":"LDRY DETER BOOSTR RECLAIM PART A 8LB 4CS","formula":"SHF40299","view":{"en":"HTTPS://IMAGES.HILLYARD.COM/IMAGES/MSDS/MSDSSHF40299.PDF","es":"HTTPS://IMAGES.HILLYARD.COM/IMAGES/MSDS/ESPSSHF40299.PDF"},"ingredients":{"en":null}},{"desc":"HERBICIDE WEED A CIDE CF 5 GAL PAIL","formula":"AMR1025591","view":{"en":"HTTPS://IMAGES.HILLYARD.COM/IMAGES/MSDS/MSDSAMR1025591.PDF","es":"HTTPS://IMAGES.HILLYARD.COM/IMAGES/MSDS/ESPSAMR1025591.PDF"},"ingredients":{"en":null}},{"desc":"$REMOVECONTENDER GYM FINISH PT A  FOR 279 BULK","formula":"HIL0020100","view":{},"ingredients":{}},{"desc":"WINDEX GLASS CLEANER 5 GL BAG IN A BOX","formula":"DRK90122","view":{"en":"HTTPS://IMAGES.HILLYARD.COM/IMAGES/MSDS/MSDSDRK90122.PDF","es":"HTTPS://IMAGES.HILLYARD.COM/IMAGES/MSDS/ESPSDRK90122.PDF"},"ingredients":{"en":null}},{"desc":"CONCRETE SEAL HVY TRAFF BEIGE PT A 1 GAL","formula":"PART50206A","view":{"en":"HTTPS://IMAGES.HILLYARD.COM/IMAGES/MSDS/MSDSHIL00502PARTA.PDF","es":"HTTPS://IMAGES.HILLYARD.COM/IMAGES/MSDS/ESPHIL00502PARTA.PDF"},"ingredients":{"en":null}},{"desc":"CONCRETE SEAL HVY TRAFF BEIGE PT A 5 GAL","formula":"PART50207A","view":{"en":"HTTPS://IMAGES.HILLYARD.COM/IMAGES/MSDS/MSDSHIL00502PARTA.PDF","es":"HTTPS://IMAGES.HILLYARD.COM/IMAGES/MSDS/ESPHIL00502PARTA.PDF"},"ingredients":{"en":null}},{"desc":"SPIC & SPAN A/P & GLASS CLNR 8/32OZ CS","formula":"PG08019","view":{"en":"HTTPS://IMAGES.HILLYARD.COM/IMAGES/MSDS/MSDSPGS67451.PDF","es":"HTTPS://IMAGES.HILLYARD.COM/IMAGES/MSDS/ESPSPGS67451.PDF"},"ingredients":{"en":null}},{"desc":"$REMOVECONCRETE SEAL HEAVY TRAF-CLR HTC PT A BU","formula":"PART49300A","view":{},"ingredients":{}},{"desc":"CONCRETE SEAL HVY TRAFF GRAY PT A 1 GAL","formula":"PART50006A","view":{"en":"HTTPS://IMAGES.HILLYARD.COM/IMAGES/MSDS/MSDSHIL00500 PART A.PDF","es":"HTTPS://IMAGES.HILLYARD.COM/IMAGES/MSDS/ESPSHIL00500 PART A.PDF"},"ingredients":{"en":null}},{"desc":"CONCRETE SEAL HVY TRAFF GRAY PT A 5 GAL","formula":"PART50007A","view":{"en":"HTTPS://IMAGES.HILLYARD.COM/IMAGES/MSDS/MSDSPART500A.PDF","es":"HTTPS://IMAGES.HILLYARD.COM/IMAGES/MSDS/ESPSPART500A.PDF"},"ingredients":{"en":null}},{"desc":"LIME A WAY IMPACT TRIGGER 12/16 OZ/CS","formula":"REC392167","view":{"en":"HTTPS://IMAGES.HILLYARD.COM/IMAGES/MSDS/MSDSREC392167.PDF","es":"HTTPS://IMAGES.HILLYARD.COM/IMAGES/MSDS/ESPSREC392167.PDF"},"ingredients":{"en":null}},{"desc":"CHARIOT I EXTRACT W/234 A/H AGM BATT","formula":"WIN98404790","view":{"en":"HTTPS://IMAGES.HILLYARD.COM/IMAGES/MSDS/MSDSADV315891.PDF","es":"HTTPS://IMAGES.HILLYARD.COM/IMAGES/MSDS/ESPSADV315891.PDF"},"ingredients":{"en":null}},{"desc":"WINDEX GLASS CLEANER 5 GL BAG IN A BOX","formula":"DRA90122","view":{"en":"HTTPS://IMAGES.HILLYARD.COM/IMAGES/MSDS/MSDSDRA90122.PDF","es":"HTTPS://IMAGES.HILLYARD.COM/IMAGES/MSDS/ESPSDRA90122.PDF"},"ingredients":{"en":null}},{"desc":"CONTENDER GYM FIN PT A FOR 1 GAL 279","formula":"HIL0020130","view":{"en":"HTTPS://IMAGES.HILLYARD.COM/IMAGES/MSDS/MSDSHIL00279A.PDF","es":"HTTPS://IMAGES.HILLYARD.COM/IMAGES/MSDS/ESPHIL00201A.PDF"},"ingredients":{"en":null}},{"desc":"CHARIOT I EXTRACT W/234 A/H BATT VAL PK","formula":"WIN98404800","view":{"en":"HTTPS://IMAGES.HILLYARD.COM/IMAGES/MSDS/MSDSTRO27GEL.PDF","es":"HTTPS://IMAGES.HILLYARD.COM/IMAGES/MSDS/ESPSTRO27GEL.PDF"},"ingredients":{"en":null}},{"desc":"CONSUME DROP-IN-A-DRAIN 2 TUB OF 168 CS","formula":"SPN320501","view":{"en":"HTTPS://IMAGES.HILLYARD.COM/IMAGES/MSDS/MSDSSPN320501.PDF","es":"HTTPS://IMAGES.HILLYARD.COM/IMAGES/MSDS/ESPSSPN320501.PDF"},"ingredients":{"en":null}},{"desc":"BORAX HAND SOAP 10  5 LB BOXES TO A CASE","formula":"DIA02203BX","view":{"en":"HTTPS://IMAGES.HILLYARD.COM/IMAGES/MSDS/MSDSDIA02203.PDF","es":"HTTPS://IMAGES.HILLYARD.COM/IMAGES/MSDS/ESPSDIA02203.PDF"},"ingredients":{"en":null}},{"desc":"CONTENDER GYM FIN PT A FOR 5 GAL 279 350","formula":"HIL0020134","view":{"en":"HTTPS://IMAGES.HILLYARD.COM/IMAGES/MSDS/MSDSHIL00279A.PDF","es":"HTTPS://IMAGES.HILLYARD.COM/IMAGES/MSDS/ESPHIL00201A.PDF"},"ingredients":{"en":null}}],"pagination":{"pageSize":100,"currentPage":0,"sort":null,"numberOfPages":1,"totalNumberOfResults":77}}
