{"results":[{"desc":"WT BOILER HW TEST KIT","formula":"ANDPTK1200","view":{"en":"HTTPS://IMAGES.HILLYARD.COM/IMAGES/MSDS/MSDSANDPTK1200.PDF","es":"HTTPS://IMAGES.HILLYARD.COM/IMAGES/MSDS/ESPSANDPTK1200.PDF"},"ingredients":{"en":null}},{"desc":"DETERGENT DISH EXTRA STRENGTH HW 4 8 LB","formula":"SHF40953","view":{"en":"HTTPS://IMAGES.HILLYARD.COM/IMAGES/MSDS/MSDSSHF40953.PDF","es":"HTTPS://IMAGES.HILLYARD.COM/IMAGES/MSDS/ESPSSHF40953.PDF"},"ingredients":{"en":null}},{"desc":"SOAP HW ANTIBAC FM ORG BLOSSOM 1250ML 3B","formula":"NSN8520015562576","view":{"en":"HTTPS://IMAGES.HILLYARD.COM/IMAGES/MSDS/MSDSNSN8520015562576.PDF","es":"HTTPS://IMAGES.HILLYARD.COM/IMAGES/MSDS/ESPSNSN8520015562576.PDF"},"ingredients":{"en":null}},{"desc":"SOAP HW LTX12 FM RFL POMEBERRY 1200ML 2B","formula":"NSN8520016492723","view":{"en":"HTTPS://IMAGES.HILLYARD.COM/IMAGES/MSDS/MSDSNSN8520016492723.PDF","es":"HTTPS://IMAGES.HILLYARD.COM/IMAGES/MSDS/ESPSNSN8520016492723.PDF"},"ingredients":{"en":null}},{"desc":"SOAP HW LTX 12 FM REFILL PLUM 1200ML 1EA","formula":"NSN8520016492724","view":{"en":"HTTPS://IMAGES.HILLYARD.COM/IMAGES/MSDS/MSDSNSN8520016492724.PDF","es":"HTTPS://IMAGES.HILLYARD.COM/IMAGES/MSDS/ESPSNSN8520016492724.PDF"},"ingredients":{"en":null}}],"pagination":{"pageSize":100,"currentPage":0,"sort":null,"numberOfPages":1,"totalNumberOfResults":5}}
